tv/__init__.py
tv/data.py
tv/exceptions.py
tv/tv.py
tv/tvdb.py
tv_series-1.0.0.dist-info/METADATA
tv_series-1.0.0.dist-info/WHEEL
tv_series-1.0.0.dist-info/entry_points.txt
tv_series-1.0.0.dist-info/top_level.txt
tv_series-1.0.0.dist-info/RECORD
