Metadata-Version: 2.1
Name: tv-series
Version: 1.0.0
Summary: UNKNOWN
Home-page: https://gitlab.com/kvikshaug/tv
Author: Ali Kaafarani
Author-email: ali@kvikshaug.no
License: UNKNOWN
Platform: UNKNOWN
Requires-Dist: click
Requires-Dist: requests
Requires-Dist: tabulate
Requires-Dist: xdg
Provides-Extra: dev
Requires-Dist: black ; extra == 'dev'
Requires-Dist: flake8 ; extra == 'dev'
Requires-Dist: flake8-bugbear ; extra == 'dev'
Requires-Dist: isort ; extra == 'dev'
